BSD-LICENSE
MANIFEST.in
README.txt
setup.py
django_twittersync_extended.egg-info/PKG-INFO
django_twittersync_extended.egg-info/SOURCES.txt
django_twittersync_extended.egg-info/dependency_links.txt
django_twittersync_extended.egg-info/requires.txt
django_twittersync_extended.egg-info/top_level.txt
twittersync/__init__.py
twittersync/admin.py
twittersync/helpers.py
twittersync/managers.py
twittersync/models.py
twittersync/settings.py
twittersync/tests.py
twittersync/management/__init__.py
twittersync/management/commands/__init__.py
twittersync/management/commands/sync_twitter_accounts.py
twittersync/management/commands/sync_twitter_accounts_parallel.py
twittersync/migrations/0001_initial.py
twittersync/migrations/0002_auto__add_field_twitteraccount_category__add_field_twitteraccount_phot.py
twittersync/migrations/__init__.py
twittersync/templatetags/__init__.py
twittersync/templatetags/twittersync_tags.py