Metadata-Version: 1.0
Name: django-twittersync-extended
Version: 0.2.1
Summary: Django app to sync Twitter stream to local DB with extendible  models. Fork of Peter Sanchez's Twitter sync
Home-page: http://bitbucket.org/mpiz/django-twittersync
Author: Martino Pizzol
Author-email: martino@ahref.eu
License: BSD License
Platform: any
Classifier: Development Status :: 4 - Beta
Classifier: Intended Audience :: Developers
Classifier: License :: OSI Approved :: BSD License
Classifier: Natural Language :: English
Classifier: Operating System :: OS Independent
Classifier: Programming Language :: Python
Classifier: Environment :: Web Environment
